{"name":"随机查询","slug":"随机查询","count":1,"postlist":[{"title":"ES 随机查询","uid":"2d77fc843e6a4b44f155d2170280baf0","slug":"ES 随机查询","date":"2022-12-23T04:50:04.000Z","updated":"2025-04-30T08:11:18.833Z","comments":true,"path":"api/articles/ES 随机查询.json","keywords":null,"cover":null,"text":"根据官方文档使用随机评分查询, 随机因子设置为当前时间, 即可实现指定条件的随机数据查询. 参考文档: ELK第七篇:spring-boot-starter-d...","permalink":"/post/ES 随机查询","photos":[],"count_time":{"symbolsCount":"2.8k","symbolsTime":"3 mins."},"categories":[{"name":"ES","slug":"ES","count":1,"path":"api/categories/ES.json"}],"tags":[{"name":"ES","slug":"ES","count":1,"path":"api/tags/ES.json"},{"name":"随机查询","slug":"随机查询","count":1,"path":"api/tags/随机查询.json"}],"author":{"name":"Weiba","slug":"blog-author","avatar":"https://avatars.githubusercontent.com/u/24520686?v=4","link":"/","description":"啊 又忘了更新了！","socials":{"github":"https://github.com/xweiba","twitter":"","stackoverflow":"","wechat":"","qq":"","weibo":"","zhihu":"","csdn":"","juejin":"","customs":{}}}}]}